easyyoutubemusic/__init__.py
easyyoutubemusic/downloader.py
easyyoutubemusic/main.py
easyyoutubemusic/song_utils.py
easyyoutubemusic/utils.py
easyyoutubemusic/youtube_api.py
EasyYoutubeMusic-1.0.0.dist-info/LICENSE
EasyYoutubeMusic-1.0.0.dist-info/METADATA
EasyYoutubeMusic-1.0.0.dist-info/WHEEL
EasyYoutubeMusic-1.0.0.dist-info/top_level.txt
EasyYoutubeMusic-1.0.0.dist-info/RECORD
