Metadata-Version: 2.1
Name: EasyYoutubeMusic
Version: 1.0.0
Summary: Python command-line tool to download your YouTube music.
Home-page: https://github.com/fifiman/EasyYoutubeMusic
Author: Nenad Bauk
Author-email: bauk.nenad@gmail.com
License: UNKNOWN
Platform: UNKNOWN
Classifier: Programming Language :: Python :: 2
Classifier: Operating System :: OS Independent
